postcache/__init__.py
postcache/cache.py
postcache-0.1.0.dist-info/RECORD
postcache-0.1.0.dist-info/top_level.txt
postcache-0.1.0.dist-info/metadata.json
postcache-0.1.0.dist-info/WHEEL
postcache-0.1.0.dist-info/METADATA
postcache-0.1.0.dist-info/DESCRIPTION.rst
