Metadata-Version: 2.0
Name: postcache
Version: 0.1.0
Summary: A Python library to cache data that is being 
Home-page: https://github.com/pddenhar/python-post-cache
Author: Peter Den Hartog
Author-email: pddenhar@gmail.com
License: UNKNOWN
Platform: UNKNOWN
